econpizza/__init__.py
econpizza/__version__.py
econpizza/config.py
econpizza/tools.py
econpizza/examples/__init__.py
econpizza/examples/bh.yml
econpizza/examples/dsge.yml
econpizza/examples/ghls.yml
econpizza/examples/hank2.yml
econpizza/examples/hank2_functions.py
econpizza/examples/hank2_no_capital.yml
econpizza/examples/hank_banking.yml
econpizza/examples/hank_banking_functions.py
econpizza/examples/hank_climate.yml
econpizza/examples/hank_climate_functions.py
econpizza/examples/hank_functions.py
econpizza/examples/hank_labor.yml
econpizza/examples/hank_labor_functions.py
econpizza/examples/hank_with_comments.yml
econpizza/examples/nk.yml
econpizza/examples/tank.yml
econpizza/parser/__init__.py
econpizza/parser/build_generic_functions.py
econpizza/parser/checks.py
econpizza/parser/compile_model_functions.py
econpizza/parser/het_agent_base_funcs.py
econpizza/solvers/shooting.py
econpizza/solvers/solve_linear.py
econpizza/solvers/solve_linear_state_space.py
econpizza/solvers/stacking.py
econpizza/solvers/steady_state.py
econpizza/testing/test_jax_bug.py
econpizza/testing/test_nb_hank1.py
econpizza/testing/test_nb_hank2.py
econpizza/testing/test_nb_quickstart.py
econpizza/testing/test_nb_rank.py
econpizza/testing/test_nb_under_the_hood.py
econpizza/testing/test_rest.py
econpizza/testing/test_rest_config.py
econpizza/testing/cache/bh.npy
econpizza/testing/cache/hank_labor.npy
econpizza/testing/cache/hank_solid.npy
econpizza/utilities/dists.py
econpizza/utilities/grids.py
econpizza/utilities/interp.py
econpizza/utilities/jacobian.py
econpizza/utilities/newton.py
econpizza-0.6.9.dist-info/licenses/LICENSE
econpizza-0.6.9.dist-info/METADATA
econpizza-0.6.9.dist-info/WHEEL
econpizza-0.6.9.dist-info/top_level.txt
econpizza-0.6.9.dist-info/RECORD
