Metadata-Version: 2.4
Name: econpizza
Version: 0.6.9
Summary: Solve nonlinear perfect foresight models with heterogeneous agents
Home-page: https://github.com/gboehl/econpizza
Author: Gregor Boehl
Author-email: admin@gregorboehl.com
License: MIT
Classifier: License :: OSI Approved :: MIT License
Classifier: Programming Language :: Python :: 3
Classifier: Programming Language :: Python :: 3.9
License-File: LICENSE
Requires-Dist: jax>=0.5.3
Requires-Dist: grgrjax>=0.4.7
Requires-Dist: pyyaml
Requires-Dist: scipy
Provides-Extra: linear
Requires-Dist: grgrlib>=0.1.22; extra == "linear"
Dynamic: author
Dynamic: author-email
Dynamic: classifier
Dynamic: description
Dynamic: description-content-type
Dynamic: home-page
Dynamic: license
Dynamic: license-file
Dynamic: provides-extra
Dynamic: requires-dist
Dynamic: summary
